qbosdk/__init__.py
qbosdk/exceptions.py
qbosdk/qbosdk.py
qbosdk/apis/__init__.py
qbosdk/apis/accounts.py
qbosdk/apis/api_base.py
qbosdk/apis/attachments.py
qbosdk/apis/bill_payments.py
qbosdk/apis/bills.py
qbosdk/apis/classes.py
qbosdk/apis/company_info.py
qbosdk/apis/customers.py
qbosdk/apis/departments.py
qbosdk/apis/employees.py
qbosdk/apis/exchange_rates.py
qbosdk/apis/items.py
qbosdk/apis/journal_entries.py
qbosdk/apis/preferences.py
qbosdk/apis/purchases.py
qbosdk/apis/tax_codes.py
qbosdk/apis/tax_rates.py
qbosdk/apis/vendors.py
qbosdk-1.4.2.dist-info/licenses/LICENSE
test/__init__.py
test/common/__init__.py
test/common/utilities.py
test/integration/__init__.py
test/integration/conftest.py
test/integration/test_qbo.py
qbosdk-1.4.2.dist-info/METADATA
qbosdk-1.4.2.dist-info/WHEEL
qbosdk-1.4.2.dist-info/top_level.txt
qbosdk-1.4.2.dist-info/RECORD
