Metadata-Version: 2.4
Name: qbosdk
Version: 1.4.2
Summary: Python SDK for accessing Quickbooks Online APIs
Home-page: https://github.com/fylein/qbo-sdk-py
Author: Shwetabh Kumar
Author-email: shwetabh.kumar@fyle.in
License: MIT
Keywords: quickbooks-online,quickbooks,fyle,api,python,sdk
Classifier: Topic :: Internet :: WWW/HTTP
Classifier: Intended Audience :: Developers
Classifier: Programming Language :: Python :: 3
Classifier: License :: OSI Approved :: MIT License
Classifier: Operating System :: OS Independent
License-File: LICENSE
Requires-Dist: requests>=2.25.0
Dynamic: author
Dynamic: author-email
Dynamic: classifier
Dynamic: description
Dynamic: description-content-type
Dynamic: home-page
Dynamic: keywords
Dynamic: license
Dynamic: license-file
Dynamic: requires-dist
Dynamic: summary
